README.md
setup.py
co6co.db_ext.egg-info/PKG-INFO
co6co.db_ext.egg-info/SOURCES.txt
co6co.db_ext.egg-info/dependency_links.txt
co6co.db_ext.egg-info/requires.txt
co6co.db_ext.egg-info/top_level.txt
co6co.db_ext.egg-info/zip-safe
co6co_db_ext/__init__.py
co6co_db_ext/db_filter.py
co6co_db_ext/db_operations.py
co6co_db_ext/db_session.py
co6co_db_ext/db_utils.py
co6co_db_ext/page_param.py
co6co_db_ext/po.py
co6co_db_ext/session.py