Metadata-Version: 2.1
Name: co6co.db-ext
Version: 0.0.15
Summary: db 数据库扩展
Home-page: http://github.com/co6co
Author: co6co
Author-email: co6co@qq.com
Classifier: Programming Language :: Python :: 3
Classifier: Programming Language :: Python :: 3.6
Requires-Dist: co6co
Requires-Dist: aiomysql
Requires-Dist: SQLAlchemy
